README.md
setup.cfg
setup.py
lib/sjb/__init__.py
lib/sjb/constants.py
lib/sjb/common/__init__.py
lib/sjb/common/base.py
lib/sjb/common/config.py
lib/sjb/common/misc.py
lib/sjb/td/__init__.py
lib/sjb/td/classes.py
lib/sjb/td/display.py
lib/sjb/td/fileio.py
lib/sjb/td/main.py
lib/sjb_todo.egg-info/PKG-INFO
lib/sjb_todo.egg-info/SOURCES.txt
lib/sjb_todo.egg-info/dependency_links.txt
lib/sjb_todo.egg-info/entry_points.txt
lib/sjb_todo.egg-info/requires.txt
lib/sjb_todo.egg-info/top_level.txt