Metadata-Version: 1.2
Name: sjb-todo
Version: 0.1.2.dev12
Summary: A simple CLI program to create, maintain and edit todo lists
Home-page: https://github.com/sicklybeans/sjb_todo
Author: Sam Bryant
Author-email: sbryant1014@gmail.com
License: MIT License
Platform: UNKNOWN
Classifier: Development Status :: 2 - Pre-Alpha
Classifier: Environment :: Console
Classifier: License :: OSI Approved :: MIT License
Classifier: Programming Language :: Python :: 3
Classifier: Topic :: Office/Business
Requires-Python: >=3
